chess_cli/__init__.py
chess_cli/chess_cli.py
chess_cli_python_stockfish-1.0.0.dist-info/METADATA
chess_cli_python_stockfish-1.0.0.dist-info/WHEEL
chess_cli_python_stockfish-1.0.0.dist-info/entry_points.txt
chess_cli_python_stockfish-1.0.0.dist-info/top_level.txt
chess_cli_python_stockfish-1.0.0.dist-info/RECORD
